README.rst
setup.py
unique_sam/__init__.py
unique_sam/unique_sam.py
unique_sam.egg-info/PKG-INFO
unique_sam.egg-info/SOURCES.txt
unique_sam.egg-info/dependency_links.txt
unique_sam.egg-info/entry_points.txt
unique_sam.egg-info/requires.txt
unique_sam.egg-info/top_level.txt