Metadata-Version: 1.1
Name: unique-sam
Version: 0.1.4
Summary: Analyse sam file and keep the unique aligment record.
Home-page: https://github.com/dlmeduLi/uniqe-sam
Author: dlmeduLi
Author-email: dlmeduLi@163.com
License: BSD
Keywords: bioinformatic samfile unique
Platform: UNKNOWN
Classifier: Development Status :: 3 - Alpha
Classifier: Topic :: Scientific/Engineering :: Bio-Informatics
Classifier: License :: OSI Approved :: BSD License
